intlevpy-0.0.7.dist-info/licenses/LICENSE
src/__init__.py
src/classification.py
src/data_loader.py
src/moments.py
src/optimization.py
src/processes.py
src/utils.py
src/tests/__init__.py
src/tests/test_classification.py
src/tests/test_moments.py
src/tests/test_optimization.py
src/tests/test_processes.py
intlevpy-0.0.7.dist-info/METADATA
intlevpy-0.0.7.dist-info/WHEEL
intlevpy-0.0.7.dist-info/top_level.txt
intlevpy-0.0.7.dist-info/RECORD
