Metadata-Version: 2.4
Name: IntLevPy
Version: 0.0.7
Summary: A Python toolkit for simulating intermittent search and Levy walk.
Home-page: https://github.com/shailendrabhandari/IntLevy-Processes
Author: Shailendra Bhandari
Author-email: shailendra.bhandari@oslomet.no
Classifier: Programming Language :: Python :: 3
Classifier: License :: OSI Approved :: MIT License
Classifier: Operating System :: OS Independent
Requires-Python: >=3.6
License-File: LICENSE
Dynamic: author
Dynamic: author-email
Dynamic: classifier
Dynamic: description
Dynamic: description-content-type
Dynamic: home-page
Dynamic: license-file
Dynamic: requires-python
Dynamic: summary
